pyske/__init__.py
pyske/core/__init__.py
pyske/core/list/__init__.py
pyske/core/list/plist.py
pyske/core/list/slist.py
pyske/core/support/__init__.py
pyske/core/support/errors.py
pyske/core/support/generate.py
pyske/core/support/parallel.py
pyske/core/support/separate.py
pyske/core/tree/__init__.py
pyske/core/tree/btree.py
pyske/core/tree/ltree.py
pyske/core/tree/ptree.py
pyske/core/tree/rtree.py
pyske/examples/__init__.py
pyske/examples/list/__init__.py
pyske/examples/list/hello_world.py
pyske/examples/list/performance.py
pyske/examples/list/variance.py
pyske/examples/tree/__init__.py
pyske/examples/tree/ancestors.py
pyske/examples/tree/generate.py
pyske/examples/tree/hello_world.py
pyske/examples/tree/prefix.py
pyske/examples/tree/separate.py
pyske/examples/tree/size.py
pyske/examples/tree/size_by_node.py
pyske/examples/tree/sumv.py
pyske/test/__init__.py
pyske/test/list/__init__.py
pyske/test/list/test_plist.py
pyske/test/list/test_slist.py
pyske/test/tree/__init__.py
pyske/test/tree/test_btree.py
pyske/test/tree/test_ltree.py
pyske/test/tree/test_ptree.py
pyske/test/tree/test_rtree.py
pyske/test/tree/test_segment.py
pyske/test/tree/test_serialization.py
pyske/test/tree/test_vtag.py
pyske-0.1.1.data/scripts/psk
pyske-0.1.1.dist-info/LICENSE.txt
pyske-0.1.1.dist-info/METADATA
pyske-0.1.1.dist-info/WHEEL
pyske-0.1.1.dist-info/top_level.txt
pyske-0.1.1.dist-info/RECORD
