Metadata-Version: 2.1
Name: pyske
Version: 0.1.1
Summary: A package for Python Skeletons using mpi4py
Home-page: UNKNOWN
Author: Jolan Philippe and Frederic Loulergue
Author-email: jp2589@nau.edu, frederic.loulergue@nau.edu
License: MIT
Platform: UNKNOWN
Classifier: Programming Language :: Python :: 3
Classifier: License :: OSI Approved :: MIT License
Classifier: Operating System :: OS Independent
Requires-Dist: mpi4py
